modelrunner/.gitignore
modelrunner/__init__.py
modelrunner/__main__.py
modelrunner/_version.py
modelrunner/config.py
modelrunner/py.typed
modelrunner/utils.py
modelrunner/model/__init__.py
modelrunner/model/base.py
modelrunner/model/factory.py
modelrunner/model/parameters.py
modelrunner/run/__init__.py
modelrunner/run/__main__.py
modelrunner/run/job.py
modelrunner/run/launch.py
modelrunner/run/results.py
modelrunner/run/compatibility/__init__.py
modelrunner/run/compatibility/triage.py
modelrunner/run/compatibility/version0.py
modelrunner/run/compatibility/version1.py
modelrunner/run/compatibility/version2.py
modelrunner/run/templates/background.jinja
modelrunner/run/templates/foreground.jinja
modelrunner/run/templates/qsub.jinja
modelrunner/run/templates/srun.jinja
modelrunner/storage/__init__.py
modelrunner/storage/access_modes.py
modelrunner/storage/attributes.py
modelrunner/storage/base.py
modelrunner/storage/group.py
modelrunner/storage/tools.py
modelrunner/storage/trajectory.py
modelrunner/storage/utils.py
modelrunner/storage/backend/__init__.py
modelrunner/storage/backend/hdf.py
modelrunner/storage/backend/json.py
modelrunner/storage/backend/memory.py
modelrunner/storage/backend/text_base.py
modelrunner/storage/backend/utils.py
modelrunner/storage/backend/yaml.py
modelrunner/storage/backend/zarr.py
py_modelrunner-0.19.1.dist-info/licenses/LICENSE
py_modelrunner-0.19.1.dist-info/METADATA
py_modelrunner-0.19.1.dist-info/WHEEL
py_modelrunner-0.19.1.dist-info/top_level.txt
py_modelrunner-0.19.1.dist-info/RECORD
