Metadata-Version: 2.4
Name: py-modelrunner
Version: 0.19.1
Summary: Python classes for organizing (HPC) simulations
Author-email: David Zwicker <david.zwicker@ds.mpg.de>
License: MIT
Project-URL: homepage, https://github.com/zwicker-group/py-modelrunner
Project-URL: documentation, http://py-modelrunner.readthedocs.io
Project-URL: repository, https://github.com/zwicker-group/py-modelrunner
Classifier: Development Status :: 4 - Beta
Classifier: Intended Audience :: Developers
Classifier: Intended Audience :: Science/Research
Classifier: Topic :: Scientific/Engineering
Classifier: Topic :: Utilities
Classifier: License :: OSI Approved :: MIT License
Classifier: Programming Language :: Python :: 3
Classifier: Programming Language :: Python :: 3.9
Classifier: Programming Language :: Python :: 3.10
Classifier: Programming Language :: Python :: 3.11
Classifier: Programming Language :: Python :: 3.12
Classifier: Programming Language :: Python :: 3.13
Requires-Python: <3.14,>=3.9
License-File: LICENSE
Requires-Dist: jinja2>=3
Requires-Dist: numpy>=1.18.0
Requires-Dist: tqdm>=4.45
Requires-Dist: numcodecs>=0.10
Provides-Extra: all
Requires-Dist: h5py>=3.5; extra == "all"
Requires-Dist: pandas>=1.3; extra == "all"
Requires-Dist: PyYAML>=5; extra == "all"
Requires-Dist: zarr<3,>=2; extra == "all"
Provides-Extra: test
Requires-Dist: black>=19; extra == "test"
Requires-Dist: isort>=5.1; extra == "test"
Requires-Dist: pytest>=5.4; extra == "test"
Requires-Dist: pytest-cov>=2.8; extra == "test"
Requires-Dist: pytest-xdist>=1.30; extra == "test"
Requires-Dist: py-pde>=0.33; extra == "test"
Requires-Dist: mypy>=0.770; extra == "test"
Dynamic: license-file
